muckrock/.pylintrc
muckrock/__init__.py
muckrock/agencies.py
muckrock/base.py
muckrock/client.py
muckrock/communications.py
muckrock/exceptions.py
muckrock/files.py
muckrock/jurisdictions.py
muckrock/organizations.py
muckrock/projects.py
muckrock/requests.py
muckrock/tests.py
muckrock/toolbox.py
muckrock/users.py
python_muckrock-2.2.0.dist-info/METADATA
python_muckrock-2.2.0.dist-info/WHEEL
python_muckrock-2.2.0.dist-info/licenses/LICENSE
python_muckrock-2.2.0.dist-info/RECORD
